byted_overpass_life_open_meta/__init__.py
byted_overpass_life_open_meta-0.0.1.dist-info/METADATA
byted_overpass_life_open_meta-0.0.1.dist-info/WHEEL
byted_overpass_life_open_meta-0.0.1.dist-info/top_level.txt
byted_overpass_life_open_meta-0.0.1.dist-info/RECORD
